split_mysql/__init__.py
split_mysql/_parser4mysql_Darwin.h
split_mysql/_parser4mysql_Darwin.so
split_mysql/_parser4mysql_Linux.h
split_mysql/_parser4mysql_Linux.so
split_mysql/build_me.sh
split_mysql/go.mod
split_mysql/go.sum
split_mysql/init_go.sh
split_mysql/parser4mysql.go
split_mysql-1.0.1.dist-info/WHEEL
split_mysql-1.0.1.dist-info/METADATA
split_mysql-1.0.1.dist-info/RECORD
