Metadata-Version: 2.1
Name: split-mysql
Version: 1.0.1
Summary: Split statements for MySQL
Author: ITXiaoPang
Author-email: itxiaopang.djh@gmail.com
Requires-Python: >=3.7,<4.0
Classifier: Programming Language :: Python :: 3
Classifier: Programming Language :: Python :: 3.7
Classifier: Programming Language :: Python :: 3.8
Classifier: Programming Language :: Python :: 3.9
Classifier: Programming Language :: Python :: 3.10
Classifier: Programming Language :: Python :: 3.11
